tf_fits/__init__.py
tf_fits/asciitable.py
tf_fits/bintable.py
tf_fits/image.py
tf_fits/common_functions/__init__.py
tf_fits/common_functions/tf_fits_common.py
tf_fits/common_functions/tf_fits_header.py
tf_fits/table_functions/__init__.py
tf_fits/table_functions/tf_fits_asciitable_data.py
tf_fits/table_functions/tf_fits_asciitable_header.py
tf_fits/table_functions/tf_fits_bintable_data.py
tf_fits/table_functions/tf_fits_bintable_header.py
tf_fits/test/__init__.py
tf_fits/test/test_tf_fits.py
tf_fits/test/tf_fits_test.fits
tf_fits-1.0.1.dist-info/METADATA
tf_fits-1.0.1.dist-info/WHEEL
tf_fits-1.0.1.dist-info/licenses/LICENSE.md
tf_fits-1.0.1.dist-info/RECORD
