Metadata-Version: 2.3
Name: tf-fits
Version: 1.0.1
Summary: Load FITS files into tf.data.Dataset
Project-URL: Homepage, https://github.com/wjpearson/tensorflow_fits
Project-URL: Documentation, https://tensorflow-fits.readthedocs.io/en/latest/
Project-URL: Repository, https://github.com/wjpearson/tensorflow_fits
Project-URL: Issues, https://github.com/wjpearson/tensorflow_fits/issues
Project-URL: Changelog, https://github.com/wjpearson/tensorflow_fits/blob/master/CHANGELOG.md
Author-email: "William J. Pearson" <willjamespearson@gmail.com>
Maintainer-email: "William J. Pearson" <willjamespearson@gmail.com>
License: Copyright 2020 William J. Pearson.
License-File: LICENSE.md
Keywords: astronomy,fits,image,machine learning,table,tensorflow
Classifier: Development Status :: 5 - Production/Stable
Classifier: Intended Audience :: Developers
Classifier: License :: OSI Approved :: Apache Software License
Classifier: Operating System :: OS Independent
Classifier: Programming Language :: Python
Classifier: Programming Language :: Python :: 3
Classifier: Programming Language :: Python :: 3.5
Classifier: Programming Language :: Python :: 3.6
Classifier: Programming Language :: Python :: 3.7
Classifier: Programming Language :: Python :: 3.8
Classifier: Programming Language :: Python :: 3.9
Requires-Python: >=3.5
Requires-Dist: tensorflow>=2.0.0a0
